{"2022-11-01":{"imsak":"05:19","gunes":"06:43","ogle":"12:11","ikindi":"15:01","aksam":"17:28","yatsi":"18:47"},"2022-11-02":{"imsak":"05:20","gunes":"06:44","ogle":"12:11","ikindi":"15:00","aksam":"17:27","yatsi":"18:46"},"2022-11-03":{"imsak":"05:21","gunes":"06:45","ogle":"12:11","ikindi":"14:59","aksam":"17:26","yatsi":"18:45"},"2022-11-04":{"imsak":"05:22","gunes":"06:47","ogle":"12:11","ikindi":"14:59","aksam":"17:25","yatsi":"18:44"},"2022-11-05":{"imsak":"05:23","gunes":"06:48","ogle":"12:11","ikindi":"14:58","aksam":"17:24","yatsi":"18:43"},"2022-11-06":{"imsak":"05:24","gunes":"06:49","ogle":"12:11","ikindi":"14:57","aksam":"17:22","yatsi":"18:42"},"2022-11-07":{"imsak":"05:25","gunes":"06:50","ogle":"12:11","ikindi":"14:56","aksam":"17:21","yatsi":"18:41"},"2022-11-08":{"imsak":"05:26","gunes":"06:51","ogle":"12:11","ikindi":"14:55","aksam":"17:20","yatsi":"18:40"},"2022-11-09":{"imsak":"05:27","gunes":"06:52","ogle":"12:11","ikindi":"14:54","aksam":"17:19","yatsi":"18:39"},"2022-11-10":{"imsak":"05:28","gunes":"06:53","ogle":"12:11","ikindi":"14:54","aksam":"17:18","yatsi":"18:39"},"2022-11-11":{"imsak":"05:29","gunes":"06:55","ogle":"12:11","ikindi":"14:53","aksam":"17:18","yatsi":"18:38"},"2022-11-12":{"imsak":"05:30","gunes":"06:56","ogle":"12:11","ikindi":"14:52","aksam":"17:17","yatsi":"18:37"},"2022-11-13":{"imsak":"05:31","gunes":"06:57","ogle":"12:11","ikindi":"14:51","aksam":"17:16","yatsi":"18:36"},"2022-11-14":{"imsak":"05:32","gunes":"06:58","ogle":"12:11","ikindi":"14:51","aksam":"17:15","yatsi":"18:36"},"2022-11-15":{"imsak":"05:33","gunes":"06:59","ogle":"12:12","ikindi":"14:50","aksam":"17:14","yatsi":"18:35"},"2022-11-16":{"imsak":"05:34","gunes":"07:00","ogle":"12:12","ikindi":"14:50","aksam":"17:13","yatsi":"18:34"},"2022-11-17":{"imsak":"05:35","gunes":"07:01","ogle":"12:12","ikindi":"14:49","aksam":"17:12","yatsi":"18:34"},"2022-11-18":{"imsak":"05:36","gunes":"07:02","ogle":"12:12","ikindi":"14:48","aksam":"17:12","yatsi":"18:33"},"2022-11-19":{"imsak":"05:37","gunes":"07:04","ogle":"12:12","ikindi":"14:48","aksam":"17:11","yatsi":"18:33"},"2022-11-20":{"imsak":"05:38","gunes":"07:05","ogle":"12:13","ikindi":"14:47","aksam":"17:10","yatsi":"18:32"},"2022-11-21":{"imsak":"05:39","gunes":"07:06","ogle":"12:13","ikindi":"14:47","aksam":"17:10","yatsi":"18:32"},"2022-11-22":{"imsak":"05:40","gunes":"07:07","ogle":"12:13","ikindi":"14:46","aksam":"17:09","yatsi":"18:31"},"2022-11-23":{"imsak":"05:40","gunes":"07:08","ogle":"12:13","ikindi":"14:46","aksam":"17:09","yatsi":"18:31"},"2022-11-24":{"imsak":"05:41","gunes":"07:09","ogle":"12:14","ikindi":"14:46","aksam":"17:08","yatsi":"18:30"},"2022-11-25":{"imsak":"05:42","gunes":"07:10","ogle":"12:14","ikindi":"14:45","aksam":"17:08","yatsi":"18:30"},"2022-11-26":{"imsak":"05:43","gunes":"07:11","ogle":"12:14","ikindi":"14:45","aksam":"17:07","yatsi":"18:30"},"2022-11-27":{"imsak":"05:44","gunes":"07:12","ogle":"12:14","ikindi":"14:45","aksam":"17:07","yatsi":"18:29"},"2022-11-28":{"imsak":"05:45","gunes":"07:13","ogle":"12:15","ikindi":"14:44","aksam":"17:06","yatsi":"18:29"},"2022-11-29":{"imsak":"05:46","gunes":"07:14","ogle":"12:15","ikindi":"14:44","aksam":"17:06","yatsi":"18:29"},"2022-11-30":{"imsak":"05:47","gunes":"07:15","ogle":"12:16","ikindi":"14:44","aksam":"17:06","yatsi":"18:29"},"2022-12-01":{"imsak":"05:48","gunes":"07:16","ogle":"12:16","ikindi":"14:44","aksam":"17:05","yatsi":"18:29"}}