{"2022-06-09":{"imsak":"03:04","gunes":"05:04","ogle":"12:49","ikindi":"16:49","aksam":"20:24","yatsi":"22:15"},"2022-06-10":{"imsak":"03:03","gunes":"05:04","ogle":"12:49","ikindi":"16:50","aksam":"20:24","yatsi":"22:16"},"2022-06-11":{"imsak":"03:03","gunes":"05:04","ogle":"12:49","ikindi":"16:50","aksam":"20:25","yatsi":"22:16"},"2022-06-12":{"imsak":"03:03","gunes":"05:04","ogle":"12:50","ikindi":"16:50","aksam":"20:25","yatsi":"22:17"},"2022-06-13":{"imsak":"03:02","gunes":"05:04","ogle":"12:50","ikindi":"16:50","aksam":"20:26","yatsi":"22:18"},"2022-06-14":{"imsak":"03:02","gunes":"05:04","ogle":"12:50","ikindi":"16:51","aksam":"20:26","yatsi":"22:19"},"2022-06-15":{"imsak":"03:02","gunes":"05:04","ogle":"12:50","ikindi":"16:51","aksam":"20:27","yatsi":"22:19"},"2022-06-16":{"imsak":"03:02","gunes":"05:04","ogle":"12:51","ikindi":"16:51","aksam":"20:27","yatsi":"22:20"},"2022-06-17":{"imsak":"03:02","gunes":"05:04","ogle":"12:51","ikindi":"16:51","aksam":"20:28","yatsi":"22:20"},"2022-06-18":{"imsak":"03:02","gunes":"05:04","ogle":"12:51","ikindi":"16:52","aksam":"20:28","yatsi":"22:21"},"2022-06-19":{"imsak":"03:02","gunes":"05:04","ogle":"12:51","ikindi":"16:52","aksam":"20:28","yatsi":"22:21"},"2022-06-20":{"imsak":"03:02","gunes":"05:04","ogle":"12:51","ikindi":"16:52","aksam":"20:28","yatsi":"22:21"},"2022-06-21":{"imsak":"03:02","gunes":"05:05","ogle":"12:52","ikindi":"16:52","aksam":"20:29","yatsi":"22:22"},"2022-06-22":{"imsak":"03:02","gunes":"05:05","ogle":"12:52","ikindi":"16:53","aksam":"20:29","yatsi":"22:22"},"2022-06-23":{"imsak":"03:02","gunes":"05:05","ogle":"12:52","ikindi":"16:53","aksam":"20:29","yatsi":"22:22"},"2022-06-24":{"imsak":"03:03","gunes":"05:05","ogle":"12:52","ikindi":"16:53","aksam":"20:29","yatsi":"22:22"},"2022-06-25":{"imsak":"03:03","gunes":"05:06","ogle":"12:52","ikindi":"16:53","aksam":"20:29","yatsi":"22:22"},"2022-06-26":{"imsak":"03:04","gunes":"05:06","ogle":"12:53","ikindi":"16:53","aksam":"20:29","yatsi":"22:22"},"2022-06-27":{"imsak":"03:04","gunes":"05:06","ogle":"12:53","ikindi":"16:54","aksam":"20:29","yatsi":"22:22"},"2022-06-28":{"imsak":"03:05","gunes":"05:07","ogle":"12:53","ikindi":"16:54","aksam":"20:30","yatsi":"22:22"},"2022-06-29":{"imsak":"03:05","gunes":"05:07","ogle":"12:53","ikindi":"16:54","aksam":"20:29","yatsi":"22:22"},"2022-06-30":{"imsak":"03:06","gunes":"05:08","ogle":"12:53","ikindi":"16:54","aksam":"20:29","yatsi":"22:21"},"2022-07-01":{"imsak":"03:07","gunes":"05:08","ogle":"12:54","ikindi":"16:54","aksam":"20:29","yatsi":"22:21"},"2022-07-02":{"imsak":"03:08","gunes":"05:09","ogle":"12:54","ikindi":"16:54","aksam":"20:29","yatsi":"22:21"},"2022-07-03":{"imsak":"03:08","gunes":"05:09","ogle":"12:54","ikindi":"16:54","aksam":"20:29","yatsi":"22:20"},"2022-07-04":{"imsak":"03:09","gunes":"05:10","ogle":"12:54","ikindi":"16:54","aksam":"20:29","yatsi":"22:20"},"2022-07-05":{"imsak":"03:10","gunes":"05:10","ogle":"12:54","ikindi":"16:55","aksam":"20:29","yatsi":"22:19"},"2022-07-06":{"imsak":"03:11","gunes":"05:11","ogle":"12:55","ikindi":"16:55","aksam":"20:28","yatsi":"22:19"},"2022-07-07":{"imsak":"03:12","gunes":"05:12","ogle":"12:55","ikindi":"16:55","aksam":"20:28","yatsi":"22:18"},"2022-07-08":{"imsak":"03:13","gunes":"05:12","ogle":"12:55","ikindi":"16:55","aksam":"20:28","yatsi":"22:17"},"2022-07-09":{"imsak":"03:14","gunes":"05:13","ogle":"12:55","ikindi":"16:55","aksam":"20:27","yatsi":"22:17"}}