{"2022-10-09":{"imsak":"05:32","gunes":"06:56","ogle":"12:51","ikindi":"16:01","aksam":"18:36","yatsi":"19:54"},"2022-10-10":{"imsak":"05:33","gunes":"06:57","ogle":"12:50","ikindi":"16:00","aksam":"18:34","yatsi":"19:53"},"2022-10-11":{"imsak":"05:34","gunes":"06:58","ogle":"12:50","ikindi":"15:59","aksam":"18:33","yatsi":"19:51"},"2022-10-12":{"imsak":"05:35","gunes":"06:59","ogle":"12:50","ikindi":"15:58","aksam":"18:31","yatsi":"19:50"},"2022-10-13":{"imsak":"05:36","gunes":"07:00","ogle":"12:50","ikindi":"15:56","aksam":"18:29","yatsi":"19:48"},"2022-10-14":{"imsak":"05:37","gunes":"07:01","ogle":"12:49","ikindi":"15:55","aksam":"18:28","yatsi":"19:47"},"2022-10-15":{"imsak":"05:38","gunes":"07:02","ogle":"12:49","ikindi":"15:54","aksam":"18:26","yatsi":"19:45"},"2022-10-16":{"imsak":"05:39","gunes":"07:03","ogle":"12:49","ikindi":"15:53","aksam":"18:25","yatsi":"19:44"},"2022-10-17":{"imsak":"05:40","gunes":"07:04","ogle":"12:49","ikindi":"15:52","aksam":"18:23","yatsi":"19:42"},"2022-10-18":{"imsak":"05:41","gunes":"07:05","ogle":"12:49","ikindi":"15:51","aksam":"18:22","yatsi":"19:41"},"2022-10-19":{"imsak":"05:42","gunes":"07:06","ogle":"12:48","ikindi":"15:49","aksam":"18:20","yatsi":"19:39"},"2022-10-20":{"imsak":"05:43","gunes":"07:08","ogle":"12:48","ikindi":"15:48","aksam":"18:19","yatsi":"19:38"},"2022-10-21":{"imsak":"05:44","gunes":"07:09","ogle":"12:48","ikindi":"15:47","aksam":"18:17","yatsi":"19:37"},"2022-10-22":{"imsak":"05:45","gunes":"07:10","ogle":"12:48","ikindi":"15:46","aksam":"18:16","yatsi":"19:35"},"2022-10-23":{"imsak":"05:46","gunes":"07:11","ogle":"12:48","ikindi":"15:45","aksam":"18:15","yatsi":"19:34"},"2022-10-24":{"imsak":"05:47","gunes":"07:12","ogle":"12:48","ikindi":"15:44","aksam":"18:13","yatsi":"19:33"},"2022-10-25":{"imsak":"05:48","gunes":"07:13","ogle":"12:47","ikindi":"15:43","aksam":"18:12","yatsi":"19:31"},"2022-10-26":{"imsak":"05:49","gunes":"07:14","ogle":"12:47","ikindi":"15:42","aksam":"18:10","yatsi":"19:30"},"2022-10-27":{"imsak":"05:51","gunes":"07:15","ogle":"12:47","ikindi":"15:41","aksam":"18:09","yatsi":"19:29"},"2022-10-28":{"imsak":"05:52","gunes":"07:17","ogle":"12:47","ikindi":"15:40","aksam":"18:08","yatsi":"19:28"},"2022-10-29":{"imsak":"05:53","gunes":"07:18","ogle":"12:47","ikindi":"15:39","aksam":"18:06","yatsi":"19:26"},"2022-10-30":{"imsak":"05:54","gunes":"07:19","ogle":"12:47","ikindi":"15:38","aksam":"18:05","yatsi":"19:25"},"2022-10-31":{"imsak":"05:55","gunes":"07:20","ogle":"12:47","ikindi":"15:37","aksam":"18:04","yatsi":"19:24"},"2022-11-01":{"imsak":"05:56","gunes":"07:21","ogle":"12:47","ikindi":"15:36","aksam":"18:03","yatsi":"19:23"},"2022-11-02":{"imsak":"05:57","gunes":"07:22","ogle":"12:47","ikindi":"15:35","aksam":"18:01","yatsi":"19:22"},"2022-11-03":{"imsak":"05:58","gunes":"07:24","ogle":"12:47","ikindi":"15:34","aksam":"18:00","yatsi":"19:21"},"2022-11-04":{"imsak":"05:59","gunes":"07:25","ogle":"12:47","ikindi":"15:33","aksam":"17:59","yatsi":"19:20"},"2022-11-05":{"imsak":"06:00","gunes":"07:26","ogle":"12:47","ikindi":"15:32","aksam":"17:58","yatsi":"19:19"},"2022-11-06":{"imsak":"06:01","gunes":"07:27","ogle":"12:47","ikindi":"15:31","aksam":"17:57","yatsi":"19:18"},"2022-11-07":{"imsak":"06:02","gunes":"07:28","ogle":"12:47","ikindi":"15:30","aksam":"17:56","yatsi":"19:17"},"2022-11-08":{"imsak":"06:03","gunes":"07:30","ogle":"12:47","ikindi":"15:29","aksam":"17:55","yatsi":"19:16"}}